dtiot_d2c/__init__.py
dtiot_d2c/cli/CFG.py
dtiot_d2c/cli/__init__.py
dtiot_d2c/cli/cli_command.py
dtiot_d2c/cli/config.py
dtiot_d2c/cli/configCLI.py
dtiot_d2c/cli/main.py
dtiot_d2c/cli/profile.py
dtiot_d2c/cli/profileCLI.py
dtiot_d2c/cli/profile_webapp.py
dtiot_d2c/cli/utils.py
dtiot_d2c/cli/prfmanapi/config.py
dtiot_d2c/cli/prfmanapi/main.py
dtiot_d2c/cli/prfmanapi/utils.py
dtiot_d2c/cli/prfmanapi/api_impl/api_utils.py
dtiot_d2c/cli/prfmanapi/api_impl/datamodel.py
dtiot_d2c/cli/prfmanapi/api_impl/device_report_post.py
dtiot_d2c/cli/prfmanapi/api_impl/healthz_get.py
dtiot_d2c/cli/prfmanapi/api_impl/job_get_report_file.py
dtiot_d2c/cli/prfmanapi/api_impl/profile_get.py
dtiot_d2c/cli/prfmanapi/configs/DEFAULT.py
dtiot_d2c/cli/prfmangui/ProfileEditor.py
dtiot_d2c/cli/prfmangui/ProfileManagerGui.py
dtiot_d2c/cli/prfmangui/ProfileSelector.py
dtiot_d2c/cli/prfmangui/__init__.py
dtiot_d2c/d2c/__init__.py
dtiot_d2c/d2c/consts.py
dtiot_d2c/d2c/get_response.py
dtiot_d2c/d2c/onem2m_base.py
dtiot_d2c/d2c/utils.py
dtiot_d2c/d2c/version_info.py
dtiot_d2c/d2c/application/__init__.py
dtiot_d2c/d2c/application/application.py
dtiot_d2c/d2c/application/cli.py
dtiot_d2c/d2c/application/consts.py
dtiot_d2c/d2c/commands/__init__.py
dtiot_d2c/d2c/commands/version.py
dtiot_d2c/d2c/device/__init__.py
dtiot_d2c/d2c/device/cli.py
dtiot_d2c/d2c/device/consts.py
dtiot_d2c/d2c/device/device.py
dtiot_d2c/d2c/device/message.py
dtiot_d2c/d2c/device_group/__init__.py
dtiot_d2c/d2c/device_group/cli.py
dtiot_d2c/d2c/device_group/consts.py
dtiot_d2c/d2c/device_group/device_group.py
dtiot_d2c/d2c/test/__init__.py
dtiot_d2c/d2c/test/application.py
dtiot_d2c/d2c/test/device.py
dtiot_d2c/d2c/test/device_group.py
dtiot_d2c/d2c/test/perftest_get_resource.py
dtiot_d2c/d2c/test/print_sample_test_configuration.py
dtiot_d2c/d2c/test/sample_test_configuration.py
dtiot_d2c/d2c/test/testcli_base.py
dtiot_d2c/d2c/test/utils.py
dtiot_d2c/d2c/test/verify_d2c_model.py
dtiot_d2c-0.9.9.dist-info/licenses/LICENSE
dtiot_d2c-0.9.9.dist-info/METADATA
dtiot_d2c-0.9.9.dist-info/WHEEL
dtiot_d2c-0.9.9.dist-info/entry_points.txt
dtiot_d2c-0.9.9.dist-info/top_level.txt
dtiot_d2c-0.9.9.dist-info/RECORD
