Metadata-Version: 2.4
Name: dtiot_d2c
Version: 0.9.9
Summary: Device to Cloud (D2C) command line interface
Author-email: Roland Baldin <roland.baldin@telekom.de>
License-Expression: MIT
Project-URL: Homepage, http://localhost:1313/docs/device-to-cloud/command-line-interface/about/
Project-URL: Issues, http://localhost:1313/docs/device-to-cloud/command-line-interface/about/
Classifier: Programming Language :: Python :: 3
Classifier: Operating System :: OS Independent
Requires-Python: >=3.10
License-File: LICENSE
Dynamic: license-file
